<annotations><filename>VNM_Baocaotaichinh_2020_Kiemtoan_Hopnhat_57.jpg</filename><size><width>1191</width><height>1684</height><depth>3</depth></size><object><name>table</name><bndbox><xmin>144.47891</xmin><ymin>335.78134</ymin><xmax>1084.1008</xmax><ymax>696.4856</ymax></bndbox></object><object><name>table</name><bndbox><xmin>139.92088</xmin><ymin>777.441</ymin><xmax>1074.2947</xmax><ymax>1132.2817</ymax></bndbox></object><object><name>table</name><bndbox><xmin>139.55733</xmin><ymin>1206.6079</ymin><xmax>1078.0736</xmax><ymax>1520.9523</ymax></bndbox></object></annotations>